wagtail_honeypot/__init__.py
wagtail_honeypot/apps.py
wagtail_honeypot/models.py
wagtail_honeypot/static/css/honeypot.css
wagtail_honeypot/static/js/honeypot.js
wagtail_honeypot/templates/tags/honeypot_fields.html
wagtail_honeypot/templatetags/__init__.py
wagtail_honeypot/templatetags/honeypot_tags.py
wagtail_honeypot-1.2.0.dist-info/LICENSE
wagtail_honeypot-1.2.0.dist-info/METADATA
wagtail_honeypot-1.2.0.dist-info/WHEEL
wagtail_honeypot-1.2.0.dist-info/top_level.txt
wagtail_honeypot-1.2.0.dist-info/RECORD
