Metadata-Version: 2.1
Name: wagtail-honeypot
Version: 1.2.0
Summary: Add optional honeypot protection to your Wagtail forms.
Author-email: Nick Moreton <nickmoreton@me.com>
License: 
Project-URL: Repository, https://github.com/wagtail-packages/wagtail-honeypot
Project-URL: Issues, https://github.com/wagtail-packages/wagtail-honeypot/issues
Project-URL: Changelog, https://github.com/wagtail-packages/wagtail-honeypot/blob/release/CHANGELOG
Keywords: wagtail,honeypot,forms,spam
Classifier: License :: OSI Approved :: MIT License
Classifier: Operating System :: OS Independent
Classifier: Programming Language :: Python
Classifier: Programming Language :: Python :: 3
Classifier: Programming Language :: Python :: 3.9
Classifier: Programming Language :: Python :: 3.10
Classifier: Programming Language :: Python :: 3.11
Classifier: Programming Language :: Python :: 3.12
Classifier: Framework :: Django
Classifier: Framework :: Django :: 4.2
Classifier: Framework :: Django :: 5.0
Classifier: Framework :: Wagtail
Classifier: Framework :: Wagtail :: 5
Classifier: Framework :: Wagtail :: 6
Requires-Python: >=3.9
License-File: LICENSE
Requires-Dist: Wagtail >=5.1
Provides-Extra: development
Requires-Dist: black ==24.4.2 ; extra == 'development'
Requires-Dist: flake8 ==7.1.0 ; extra == 'development'
Requires-Dist: isort ==5.13.2 ; extra == 'development'
Requires-Dist: django-upgrade ; extra == 'development'
Requires-Dist: pyupgrade ; extra == 'development'
